externTest_LucasAmmer/__init__.py
externTest_LucasAmmer/externTest.py
externTest-1.1.0.dist-info/LICENSE
externTest-1.1.0.dist-info/METADATA
externTest-1.1.0.dist-info/WHEEL
externTest-1.1.0.dist-info/top_level.txt
externTest-1.1.0.dist-info/RECORD
