Metadata-Version: 2.1
Name: externTest
Version: 1.1.0
Summary: Testing library for external executables.
Author-email: LucasAmmer <me@LucasAmmer.com>
Classifier: Programming Language :: Python :: 3
Classifier: License :: OSI Approved :: MIT License
Classifier: Operating System :: OS Independent
Requires-Python: >=3.8
License-File: LICENSE
